django_ical/__init__.py
django_ical/feedgenerator.py
django_ical/utils.py
django_ical/views.py
django_ical/tests/__init__.py
django_ical/tests/test_feed.py
django_ical/tests/test_recurrence.py
django_ical-1.9.2.dist-info/LICENSE
django_ical-1.9.2.dist-info/METADATA
django_ical-1.9.2.dist-info/WHEEL
django_ical-1.9.2.dist-info/top_level.txt
django_ical-1.9.2.dist-info/RECORD
