Metadata-Version: 2.1
Name: django-ical
Version: 1.9.2
Summary: iCal feeds for Django based on Django's syndication feed framework.
Home-page: https://github.com/jazzband/django-ical
Author: Ian Lewis
Author-email: security@jazzband.com
Maintainer: Jazzband
Maintainer-email: security@jazzband.com
License: MIT License
Keywords: ical calendar django syndication feed
Classifier: Development Status :: 5 - Production/Stable
Classifier: Environment :: Web Environment
Classifier: Environment :: Plugins
Classifier: Framework :: Django
Classifier: Framework :: Django :: 3.2
Classifier: Framework :: Django :: 4.0
Classifier: Framework :: Django :: 4.1
Classifier: Intended Audience :: Developers
Classifier: Intended Audience :: System Administrators
Classifier: License :: OSI Approved :: MIT License
Classifier: Operating System :: OS Independent
Classifier: Programming Language :: Python
Classifier: Programming Language :: Python :: 3
Classifier: Programming Language :: Python :: 3.8
Classifier: Programming Language :: Python :: 3.9
Classifier: Programming Language :: Python :: 3.10
Classifier: Programming Language :: Python :: 3.11
Classifier: Programming Language :: Python :: Implementation :: CPython
Classifier: Programming Language :: Python :: Implementation :: PyPy
Classifier: Topic :: Software Development :: Libraries :: Python Modules
License-File: LICENSE
Requires-Dist: django (>=3.2)
Requires-Dist: icalendar (>=4.0.3)
Requires-Dist: django-recurrence (>=1.11.1)
